TAD_Library/Common.py
TAD_Library/TCP_Function.py
TAD_Library/TCP_Packet_Lib.py
TAD_Library/__init__.py
TAD_Library-0.0.17.dist-info/LICENSE
TAD_Library-0.0.17.dist-info/METADATA
TAD_Library-0.0.17.dist-info/WHEEL
TAD_Library-0.0.17.dist-info/top_level.txt
TAD_Library-0.0.17.dist-info/RECORD
